s3_parse_url/__init__.py
s3_parse_url/base.py
s3_parse_url/exceptions.py
s3_parse_url/ext/__init__.py
s3_parse_url/ext/clients.py
s3_parse_url/storages/__init__.py
s3_parse_url/storages/amazon.py
s3_parse_url/storages/mail_ru.py
s3_parse_url/storages/minio.py
s3_parse_url/storages/selectel.py
s3_parse_url/storages/yandex.py
s3_parse_url-0.4.0.dist-info/METADATA
s3_parse_url-0.4.0.dist-info/WHEEL
s3_parse_url-0.4.0.dist-info/RECORD
