Metadata-Version: 2.1
Name: s3-parse-url
Version: 0.4.0
Summary: A small tool to parse URLs for S3 compatible storage services
Home-page: https://github.com/marazmiki/s3-parse-url
License: MIT
Author: Mikhail Porokhovnichenko
Author-email: marazmiki@gmail.com
Requires-Python: >=3.8.1,<4.0
Classifier: Environment :: Web Environment
Classifier: Intended Audience :: Developers
Classifier: License :: OSI Approved :: MIT License
Classifier: Operating System :: OS Independent
Classifier: Programming Language :: Python
Classifier: Programming Language :: Python :: 3
Classifier: Programming Language :: Python :: 3.9
Classifier: Programming Language :: Python :: 3.10
Classifier: Programming Language :: Python :: 3.11
Classifier: Programming Language :: Python :: 3.12
Classifier: Programming Language :: Python :: 3.8
Project-URL: Repository, https://github.com/marazmiki/s3-parse-url
